crawl_riss/__init__.py
crawl_riss/crawl_hs.py
crawl_riss/crawl_hw.py
crawl_riss-0.1.1.dist-info/LICENSE.txt
crawl_riss-0.1.1.dist-info/METADATA
crawl_riss-0.1.1.dist-info/WHEEL
crawl_riss-0.1.1.dist-info/top_level.txt
crawl_riss-0.1.1.dist-info/RECORD
